setup.cfg
setup.py
fantasy_football_auction/__init__.py
fantasy_football_auction/auction.py
fantasy_football_auction/auction_test.py
fantasy_football_auction/owner.py
fantasy_football_auction/owner_test.py
fantasy_football_auction/player.py
fantasy_football_auction/position.py
fantasy_football_auction/position_test.py
fantasy_football_auction.egg-info/PKG-INFO
fantasy_football_auction.egg-info/SOURCES.txt
fantasy_football_auction.egg-info/dependency_links.txt
fantasy_football_auction.egg-info/top_level.txt