Metadata-Version: 1.2
Name: fantasy-football-auction
Version: 0.9.95
Summary: Python library simulating a fantasy football auction. Intended to be used for AI, but you should be able to use this for other purposes as well. This task assumes that each draftable player has a specific value (for example, looking at the ratings from FantasyPros).
Home-page: https://github.com/chairbender/fantasy-football-auction
Author: Kyle Hipke
Author-email: kwhipke1@gmail.com
License: UNKNOWN
Download-URL: https://github.com/chairbender/fantasy-football-auction/archive/0.9.95.tar.gz
Keywords: AI,football,fantasy,auction
Platform: UNKNOWN
Requires-Python: >=3.6
